pd_read-0.1.1.dist-info/DESCRIPTION.rst
pd_read-0.1.1.dist-info/METADATA
pd_read-0.1.1.dist-info/RECORD
pd_read-0.1.1.dist-info/WHEEL
pd_read-0.1.1.dist-info/metadata.json
pd_read-0.1.1.dist-info/top_level.txt
pdread/__init__.py
pdread/base_class.py
pdread/pd_read.py
pdread/read_csv.py
