Metadata-Version: 2.0
Name: pd-read
Version: 0.1.1
Summary: Read csv files with the help of pandas library !!
Home-page: https://pypi.python.org/pypi/PDRead/
Author: Vikas Shrivastava
Author-email: vshri119@gmail.com
License: LICENSE.txt
Platform: UNKNOWN
Requires-Dist: numpy (>=1.18.0)
Requires-Dist: pandas (>=0.25.3)
